ard/__init__.py
ard/wind_query.py
ard/api/__init__.py
ard/api/interface.py
ard/api/default_systems/ard_system_offshore_floating.yaml
ard/api/default_systems/ard_system_offshore_floating_no_cable_design.yaml
ard/api/default_systems/ard_system_offshore_monopile.yaml
ard/api/default_systems/ard_system_offshore_monopile_no_cable_design.yaml
ard/api/default_systems/ard_system_onshore.yaml
ard/api/default_systems/ard_system_onshore_batch.yaml
ard/api/default_systems/ard_system_onshore_no_cable_design.yaml
ard/collection/__init__.py
ard/collection/optiwindnet_wrap.py
ard/collection/templates.py
ard/cost/__init__.py
ard/cost/approximate_turbine_spacing.py
ard/cost/orbit_wrap.py
ard/cost/wisdem_wrap.py
ard/farm_aero/__init__.py
ard/farm_aero/floris.py
ard/farm_aero/placeholder.py
ard/farm_aero/templates.py
ard/geographic/__init__.py
ard/geographic/geomorphology.py
ard/layout/__init__.py
ard/layout/boundary.py
ard/layout/fullfarm.py
ard/layout/gridfarm.py
ard/layout/spacing.py
ard/layout/sunflower.py
ard/layout/templates.py
ard/offshore/__init__.py
ard/offshore/mooring_constraint.py
ard/offshore/mooring_design_constant_depth.py
ard/utils/__init__.py
ard/utils/core.py
ard/utils/geometry.py
ard/utils/io.py
ard/utils/mathematics.py
ard/utils/test_utils.py
ard/viz/__init__.py
ard/viz/layout.py
ard/viz/plot_layout.py
ard_nrel-0.1.0b2.dist-info/licenses/LICENSE
ard_nrel-0.1.0b2.dist-info/METADATA
ard_nrel-0.1.0b2.dist-info/WHEEL
ard_nrel-0.1.0b2.dist-info/top_level.txt
ard_nrel-0.1.0b2.dist-info/RECORD
