Metadata-Version: 2.4
Name: ard-nrel
Version: 0.1.0b2
Summary: A package for multidisciplinary and/or multifidelity wind farm design
Author-email: Cory Frontin <cory.frontin@nrel.gov>, Rafael Mudafort <rafael.mudafort@nrel.gov>, Jared Thomas <jared.thomas@nrel.gov>
Project-URL: Documentation, https://wisdem.github.io/Ard
Project-URL: Repository, https://github.com/wisdem/Ard.git
Project-URL: Issues, https://github.com/wisdem/Ard/issues
Classifier: Development Status :: 4 - Beta
Classifier: License :: OSI Approved :: Apache Software License
Classifier: Operating System :: OS Independent
Classifier: Programming Language :: Python :: 3
Classifier: Programming Language :: Python :: 3.10
Classifier: Programming Language :: Python :: 3.11
Classifier: Programming Language :: Python :: 3.12
Requires-Python: <3.13,>=3.10
License-File: LICENSE
Requires-Dist: numpy<2.3
Requires-Dist: floris>=4.3
Requires-Dist: wisdem>=3.21
Requires-Dist: NLopt
Requires-Dist: marmot-agents
Requires-Dist: openmdao
Requires-Dist: shapely
Requires-Dist: jax
Requires-Dist: optiwindnet>=0.0.6
Requires-Dist: statsmodels
Requires-Dist: highspy
Requires-Dist: pyyaml
Requires-Dist: windio
Requires-Dist: ipykernel
Provides-Extra: dev
Requires-Dist: black[jupyter]; extra == "dev"
Requires-Dist: jupyter; extra == "dev"
Requires-Dist: pytest; extra == "dev"
Requires-Dist: pytest-cov; extra == "dev"
Requires-Dist: pytest-subtests; extra == "dev"
Provides-Extra: docs
Requires-Dist: pyxdsm; extra == "docs"
Requires-Dist: jupyter-book; extra == "docs"
Requires-Dist: sphinx-book-theme; extra == "docs"
Requires-Dist: sphinx-autodoc-typehints; extra == "docs"
Dynamic: license-file
